redbeat/__init__.py
redbeat/decoder.py
redbeat/schedulers.py
redbeat/schedules.py
celery_redbeat_meideng-0.0.2.dev0.dist-info/LICENSE
celery_redbeat_meideng-0.0.2.dev0.dist-info/METADATA
celery_redbeat_meideng-0.0.2.dev0.dist-info/WHEEL
celery_redbeat_meideng-0.0.2.dev0.dist-info/top_level.txt
celery_redbeat_meideng-0.0.2.dev0.dist-info/RECORD
