Metadata-Version: 2.1
Name: celery-redbeat-meideng
Version: 0.0.2.dev0
Summary: A Celery Beat Scheduler using Redis for persistent storage
Home-page: https://github.com/sempr/redbeat
Author: Marc Sibson
Author-email: sibson+redbeat@gmail.com
License: Apache License, Version 2.0
Keywords: python,celery,beat,redis
Platform: UNKNOWN
Classifier: Development Status :: 5 - Production/Stable
Classifier: License :: OSI Approved :: Apache Software License
Classifier: Topic :: System :: Distributed Computing
Classifier: Topic :: Software Development :: Object Brokering
Classifier: Programming Language :: Python
Classifier: Programming Language :: Python :: 2
Classifier: Programming Language :: Python :: 2.7
Classifier: Programming Language :: Python :: 3
Classifier: Programming Language :: Python :: 3.4
Classifier: Programming Language :: Python :: 3.5
Classifier: Programming Language :: Python :: Implementation :: CPython
Classifier: Operating System :: OS Independent
Requires-Dist: redis (>=3.2)
Requires-Dist: celery (>=4.2)
Requires-Dist: python-dateutil
Requires-Dist: tenacity
